pydantic_gitlab_webhooks/__init__.py
pydantic_gitlab_webhooks/_access_token_event.py
pydantic_gitlab_webhooks/_common.py
pydantic_gitlab_webhooks/_issue_event.py
pydantic_gitlab_webhooks/_job_event.py
pydantic_gitlab_webhooks/_merge_request_event.py
pydantic_gitlab_webhooks/_pipeline_event.py
pydantic_gitlab_webhooks/_release_event.py
pydantic_gitlab_webhooks/_types.py
pydantic_gitlab_webhooks/events.py
pydantic_gitlab_webhooks/hooks.py
pydantic_gitlab_webhooks/validators.py
pydantic_gitlab_webhooks-0.3.51.dist-info/METADATA
pydantic_gitlab_webhooks-0.3.51.dist-info/WHEEL
pydantic_gitlab_webhooks-0.3.51.dist-info/licenses/LICENSE.txt
pydantic_gitlab_webhooks-0.3.51.dist-info/RECORD
