Metadata-Version: 2.4
Name: pydantic-gitlab-webhooks
Version: 0.3.51
Summary: Pydantic models for GitLab webhook payloads
License: MIT
License-File: LICENSE.txt
Author: Rich Wareham
Author-email: rich.pydantic-gitlab-webhooks@richwareham.com
Requires-Python: >=3.10,<4.0
Classifier: License :: OSI Approved :: MIT License
Classifier: Programming Language :: Python :: 3
Classifier: Programming Language :: Python :: 3.10
Classifier: Programming Language :: Python :: 3.11
Classifier: Programming Language :: Python :: 3.12
Classifier: Programming Language :: Python :: 3.13
Classifier: Programming Language :: Python :: 3.14
Requires-Dist: pydantic[email] (>=2.9.2,<3.0.0)
Requires-Dist: python-dateutil (>=2.9.0.post0,<3.0.0)
Project-URL: Changelog, https://github.com/rjw57/pydantic-gitlab-webhooks/blob/main/CHANGELOG.md
Project-URL: Documentation, https://rjw57.github.io/pydantic-gitlab-webhooks
Project-URL: Homepage, https://github.com/rjw57/pydantic-gitlab-webhooks
Project-URL: Issues, https://github.com/rjw57/pydantic-gitlab-webhooks/issues
Project-URL: Repository, https://github.com/rjw57/pydantic-gitlab-webhooks.git
